{
    "numTabs":19,
    "tabs":[
        {
            "n":"empty",
            "i":0,
            "id":"eabc6b989b98c5543826b0c765fac60c3d9af6332df6b6fc782eb5d0389329613",
            "type":"NormalStash",
            "hidden":false,
            "selected":false,
            "colour":{"r":255,"g":170,"b":0},
            "srcL":"https:\/\/web.poecdn.com\/gen\/image\/WzIzLDEseyJ0IjoibCIsImMiOi04NjI5MTk0fV0\/10d10e4923\/Stash_TabL.png",
            "srcC":"https:\/\/web.poecdn.com\/gen\/image\/WzIzLDEseyJ0IjoibSIsImMiOi04NjI5MTk0fV0\/bc028daabc\/Stash_TabL.png",
            "srcR":"https:\/\/web.poecdn.com\/gen\/image\/WzIzLDEseyJ0IjoiciIsImMiOi04NjI5MTk0fV0\/6aa79009ee\/Stash_TabL.png"
        },{
            "n":"Currencies",
            "i":1,
            "id":"7c7eef2b4ee6ab81903156465083e1daf642e49c6271399deab9bda320aef856",
            "type":"CurrencyStash",
            "hidden":false,
            "selected":false,
            "colour":{"r":255,"g":170,"b":0},
            "srcL":"https:\/\/web.poecdn.com\/gen\/image\/WzIzLDEseyJ0IjoibCIsImMiOi0yMjAxNn1d\/317f9d2d8c\/Stash_TabL.png",
            "srcC":"https:\/\/web.poecdn.com\/gen\/image\/WzIzLDEseyJ0IjoibSIsImMiOi0yMjAxNn1d\/c06c5980a6\/Stash_TabL.png",
            "srcR":"https:\/\/web.poecdn.com\/gen\/image\/WzIzLDEseyJ0IjoiciIsImMiOi0yMjAxNn1d\/9a7ac3c720\/Stash_TabL.png"
        },{
            "n":"Fragments",
            "i":2,
            "id":"73cfb853d1ca8a4cf4d2f6633395d0c690e089e4bc74a98534229e0b016431ba",
            "type":"FragmentStash",
            "hidden":false,
            "selected":false,
            "colour":{"r":255,"g":170,"b":0},
            "srcL":"https:\/\/web.poecdn.com\/gen\/image\/WzIzLDEseyJ0IjoibCIsImMiOi0xMDI1NjM4NH1d\/add36a62cf\/Stash_TabL.png",
            "srcC":"https:\/\/web.poecdn.com\/gen\/image\/WzIzLDEseyJ0IjoibSIsImMiOi0xMDI1NjM4NH1d\/bca6333c61\/Stash_TabL.png",
            "srcR":"https:\/\/web.poecdn.com\/gen\/image\/WzIzLDEseyJ0IjoiciIsImMiOi0xMDI1NjM4NH1d\/1e0dc0f0ab\/Stash_TabL.png"
        },{
            "n":"Essences",
            "i":3,
            "id":"73cfb853d1ca8a4cf4d2f6633395d0c690e089e4bc74a98534229e0b016431ba",
            "type":"EssenceStash",
            "hidden":false,
            "selected":false,
            "colour":{"r":255,"g":170,"b":0},
            "srcL":"https:\/\/web.poecdn.com\/gen\/image\/WzIzLDEseyJ0IjoibCIsImMiOi0xMDI1NjM4NH1d\/add36a62cf\/Stash_TabL.png",
            "srcC":"https:\/\/web.poecdn.com\/gen\/image\/WzIzLDEseyJ0IjoibSIsImMiOi0xMDI1NjM4NH1d\/bca6333c61\/Stash_TabL.png",
            "srcR":"https:\/\/web.poecdn.com\/gen\/image\/WzIzLDEseyJ0IjoiciIsImMiOi0xMDI1NjM4NH1d\/1e0dc0f0ab\/Stash_TabL.png"
        },{
            "n":"Maps",
            "i":4,
            "id":"37a95ef56be33f1ed29dc9e612c04dbfb2180771180e939530403f5d9a6dbd2c",
            "type":"MapStash",
            "hidden":false,
            "selected":false,
            "colour":{"r":255,"g":170,"b":0},
            "srcL":"https:\/\/web.poecdn.com\/gen\/image\/WzIzLDEseyJ0IjoibCIsImMiOi0xMDg3ODc5N31d\/5e29dc2964\/Stash_TabL.png",
            "srcC":"https:\/\/web.poecdn.com\/gen\/image\/WzIzLDEseyJ0IjoibSIsImMiOi0xMDg3ODc5N31d\/29a9b1e04f\/Stash_TabL.png",
            "srcR":"https:\/\/web.poecdn.com\/gen\/image\/WzIzLDEseyJ0IjoiciIsImMiOi0xMDg3ODc5N31d\/6e0cc9951b\/Stash_TabL.png"
        },{
            "n":"Divination",
            "i":5,
            "id":"37a95ef56be33f1ed29dc9e612c04dbfb2180771180e939530403f5d9a6dbd2c",
            "type":"DivinationStash",
            "hidden":false,
            "selected":false,
            "colour":{"r":255,"g":170,"b":0},
            "srcL":"https:\/\/web.poecdn.com\/gen\/image\/WzIzLDEseyJ0IjoibCIsImMiOi0xMDg3ODc5N31d\/5e29dc2964\/Stash_TabL.png",
            "srcC":"https:\/\/web.poecdn.com\/gen\/image\/WzIzLDEseyJ0IjoibSIsImMiOi0xMDg3ODc5N31d\/29a9b1e04f\/Stash_TabL.png",
            "srcR":"https:\/\/web.poecdn.com\/gen\/image\/WzIzLDEseyJ0IjoiciIsImMiOi0xMDg3ODc5N31d\/6e0cc9951b\/Stash_TabL.png"
        },{
            "n":"1",
            "i":6,
            "id":"61201edd1ce10fc5a56698829c3d9e1d487ff284ff1e5b176b07ecf0e23ba30e",
            "type":"NormalStash",
            "hidden":false,
            "selected":false,
            "colour":{"r":255,"g":170,"b":0},
            "srcL":"https:\/\/web.poecdn.com\/gen\/image\/WzIzLDEseyJ0IjoibCIsImMiOi04NjI5MTk0fV0\/10d10e4923\/Stash_TabL.png",
            "srcC":"https:\/\/web.poecdn.com\/gen\/image\/WzIzLDEseyJ0IjoibSIsImMiOi04NjI5MTk0fV0\/bc028daabc\/Stash_TabL.png",
            "srcR":"https:\/\/web.poecdn.com\/gen\/image\/WzIzLDEseyJ0IjoiciIsImMiOi04NjI5MTk0fV0\/6aa79009ee\/Stash_TabL.png"
        },{
            "n":"Quad",
            "i":7,
            "id":"37a95ef56be33f1ed29dc9e612c04dbfb2180771180e939530403f5d9a6dbd2c",
            "type":"QuadStash",
            "hidden":false,
            "selected":false,
            "colour":{"r":255,"g":170,"b":0},
            "srcL":"https:\/\/web.poecdn.com\/gen\/image\/WzIzLDEseyJ0IjoibCIsImMiOi04NjI5MTk0fV0\/10d10e4923\/Stash_TabL.png",
            "srcC":"https:\/\/web.poecdn.com\/gen\/image\/WzIzLDEseyJ0IjoibSIsImMiOi04NjI5MTk0fV0\/bc028daabc\/Stash_TabL.png",
            "srcR":"https:\/\/web.poecdn.com\/gen\/image\/WzIzLDEseyJ0IjoiciIsImMiOi04NjI5MTk0fV0\/6aa79009ee\/Stash_TabL.png"
        },{
            "n":"4",
            "i":8,
            "id":"fde6b989b98c5543826b0c765fac60c3d9af6332df6b6fc782eb5d0389329613",
            "type":"NormalStash",
            "hidden":false,
            "selected":false,
            "colour":{"r":255,"g":170,"b":0},
            "srcL":"https:\/\/web.poecdn.com\/gen\/image\/WzIzLDEseyJ0IjoibCIsImMiOi04NjI5MTk0fV0\/10d10e4923\/Stash_TabL.png",
            "srcC":"https:\/\/web.poecdn.com\/gen\/image\/WzIzLDEseyJ0IjoibSIsImMiOi04NjI5MTk0fV0\/bc028daabc\/Stash_TabL.png",
            "srcR":"https:\/\/web.poecdn.com\/gen\/image\/WzIzLDEseyJ0IjoiciIsImMiOi04NjI5MTk0fV0\/6aa79009ee\/Stash_TabL.png"
        },{
            "n":"Jewels",
            "i":9,
            "id":"eae7f0c899fbd3d42633d158cd77c0ed74cf298d296500c4457a32dc20ee2114",
            "type":"NormalStash",
            "hidden":false,
            "selected":false,
            "colour":{"r":255,"g":170,"b":0},
            "srcL":"https:\/\/web.poecdn.com\/gen\/image\/WzIzLDEseyJ0IjoibCIsImMiOi04NjI5MTk0fV0\/10d10e4923\/Stash_TabL.png",
            "srcC":"https:\/\/web.poecdn.com\/gen\/image\/WzIzLDEseyJ0IjoibSIsImMiOi04NjI5MTk0fV0\/bc028daabc\/Stash_TabL.png",
            "srcR":"https:\/\/web.poecdn.com\/gen\/image\/WzIzLDEseyJ0IjoiciIsImMiOi04NjI5MTk0fV0\/6aa79009ee\/Stash_TabL.png"
        },{
            "n":"Unidentified",
            "i":10,
            "id":"b68aa7252eb1a2daaad09942283b167544ec4a25d4741254891e7be9e3a1595e",
            "type":"NormalStash",
            "hidden":false,
            "selected":false,
            "colour":{"r":255,"g":170,"b":0},
            "srcL":"https:\/\/web.poecdn.com\/gen\/image\/WzIzLDEseyJ0IjoibCIsImMiOi04NjI5MTk0fV0\/10d10e4923\/Stash_TabL.png",
            "srcC":"https:\/\/web.poecdn.com\/gen\/image\/WzIzLDEseyJ0IjoibSIsImMiOi04NjI5MTk0fV0\/bc028daabc\/Stash_TabL.png",
            "srcR":"https:\/\/web.poecdn.com\/gen\/image\/WzIzLDEseyJ0IjoiciIsImMiOi04NjI5MTk0fV0\/6aa79009ee\/Stash_TabL.png"
        },{
            "n":"Gems",
            "i":11,
            "id":"5c2725b4925dd84dbfd59202cc9755a7f210a56501ba25070b8330675cad4c95",
            "type":"NormalStash",
            "hidden":false,
            "selected":false,
            "colour":{"r":255,"g":170,"b":0},
            "srcL":"https:\/\/web.poecdn.com\/gen\/image\/WzIzLDEseyJ0IjoibCIsImMiOi04NjI5MTk0fV0\/10d10e4923\/Stash_TabL.png",
            "srcC":"https:\/\/web.poecdn.com\/gen\/image\/WzIzLDEseyJ0IjoibSIsImMiOi04NjI5MTk0fV0\/bc028daabc\/Stash_TabL.png",
            "srcR":"https:\/\/web.poecdn.com\/gen\/image\/WzIzLDEseyJ0IjoiciIsImMiOi04NjI5MTk0fV0\/6aa79009ee\/Stash_TabL.png"
        },{
            "n":"DivCards",
            "i":12,
            "id":"96b21d590b76b7945087b4ca6331efed61ce357b61c8171ca9ec5cfa9ae6b7f7",
            "type":"NormalStash",
            "hidden":false,
            "selected":false,
            "colour":{"r":255,"g":170,"b":0},
            "srcL":"https:\/\/web.poecdn.com\/gen\/image\/WzIzLDEseyJ0IjoibCIsImMiOi04NjI5MTk0fV0\/10d10e4923\/Stash_TabL.png",
            "srcC":"https:\/\/web.poecdn.com\/gen\/image\/WzIzLDEseyJ0IjoibSIsImMiOi04NjI5MTk0fV0\/bc028daabc\/Stash_TabL.png",
            "srcR":"https:\/\/web.poecdn.com\/gen\/image\/WzIzLDEseyJ0IjoiciIsImMiOi04NjI5MTk0fV0\/6aa79009ee\/Stash_TabL.png"
        },{
            "n":"Essence crafting",
            "i":13,
            "id":"6ce31ef5b11c4f7118b17e53d4bc4d45e17f2fe4e56895bf36deb903559c8aa4",
            "type":"NormalStash",
            "hidden":false,
            "selected":false,
            "colour":{"r":255,"g":170,"b":0},
            "srcL":"https:\/\/web.poecdn.com\/gen\/image\/WzIzLDEseyJ0IjoibCIsImMiOi04NjI5MTk0fV0\/10d10e4923\/Stash_TabL.png",
            "srcC":"https:\/\/web.poecdn.com\/gen\/image\/WzIzLDEseyJ0IjoibSIsImMiOi04NjI5MTk0fV0\/bc028daabc\/Stash_TabL.png",
            "srcR":"https:\/\/web.poecdn.com\/gen\/image\/WzIzLDEseyJ0IjoiciIsImMiOi04NjI5MTk0fV0\/6aa79009ee\/Stash_TabL.png"
        },{
            "n":"Sell",
            "i":14,
            "id":"b43b1ec34cb32f5455a6447b76f9c5eb9fe1648fc67436ec5750e0807ff98ba7",
            "type":"PremiumStash",
            "hidden":false,
            "selected":false,
            "colour":{"r":255,"g":170,"b":0},
            "srcL":"https:\/\/web.poecdn.com\/gen\/image\/WzIzLDEseyJ0IjoibCIsImMiOi00MjU5ODQwfV0\/cc64d967fb\/Stash_TabL.png",
            "srcC":"https:\/\/web.poecdn.com\/gen\/image\/WzIzLDEseyJ0IjoibSIsImMiOi00MjU5ODQwfV0\/8e5ec47efe\/Stash_TabL.png",
            "srcR":"https:\/\/web.poecdn.com\/gen\/image\/WzIzLDEseyJ0IjoiciIsImMiOi00MjU5ODQwfV0\/ff3a937d2d\/Stash_TabL.png"
        },{
            "n":"2",
            "i":15,
            "id":"983d7d025c24633991ecea1ca02332daf8764a260b60036df48ab5375a0062da",
            "type":"NormalStash",
            "hidden":false,
            "selected":false,
            "colour":{"r":255,"g":170,"b":0},
            "srcL":"https:\/\/web.poecdn.com\/gen\/image\/WzIzLDEseyJ0IjoibCIsImMiOi04NjI5MTk0fV0\/10d10e4923\/Stash_TabL.png",
            "srcC":"https:\/\/web.poecdn.com\/gen\/image\/WzIzLDEseyJ0IjoibSIsImMiOi04NjI5MTk0fV0\/bc028daabc\/Stash_TabL.png",
            "srcR":"https:\/\/web.poecdn.com\/gen\/image\/WzIzLDEseyJ0IjoiciIsImMiOi04NjI5MTk0fV0\/6aa79009ee\/Stash_TabL.png"
        },{
            "n":"3",
            "i":16,
            "id":"20b77e53ad08ad2197db235b5eec7b37b6c8b35e42bf98022998ba117e320973",
            "type":"NormalStash",
            "hidden":false,
            "selected":false,
            "colour":{"r":255,"g":170,"b":0},
            "srcL":"https:\/\/web.poecdn.com\/gen\/image\/WzIzLDEseyJ0IjoibCIsImMiOi04NjI5MTk0fV0\/10d10e4923\/Stash_TabL.png",
            "srcC":"https:\/\/web.poecdn.com\/gen\/image\/WzIzLDEseyJ0IjoibSIsImMiOi04NjI5MTk0fV0\/bc028daabc\/Stash_TabL.png",
            "srcR":"https:\/\/web.poecdn.com\/gen\/image\/WzIzLDEseyJ0IjoiciIsImMiOi04NjI5MTk0fV0\/6aa79009ee\/Stash_TabL.png"
        },{
            "n":"10",
            "i":17,
            "id":"1c073013340d4dc60d2db47c6c31ca9c6fc36767b2c24dcd2af4bb3bb595dbac",
            "type":"NormalStash",
            "hidden":false,
            "selected":true,
            "colour":{"r":255,"g":170,"b":0},
            "srcL":"https:\/\/web.poecdn.com\/gen\/image\/WzIzLDEseyJ0IjoibCIsImMiOi04NjI5MTk0fV0\/10d10e4923\/Stash_TabL.png",
            "srcC":"https:\/\/web.poecdn.com\/gen\/image\/WzIzLDEseyJ0IjoibSIsImMiOi04NjI5MTk0fV0\/bc028daabc\/Stash_TabL.png",
            "srcR":"https:\/\/web.poecdn.com\/gen\/image\/WzIzLDEseyJ0IjoiciIsImMiOi04NjI5MTk0fV0\/6aa79009ee\/Stash_TabL.png"
        },{
            "n":"Relic",
            "i":18,
            "id":"1c073013340d4dc60d2db47c6c31ca9c6fc36767b2c24dcd2af4bb3bb595dbac",
            "type":"NormalStash",
            "hidden":false,
            "selected":true,
            "colour":{"r":255,"g":170,"b":0},
            "srcL":"https:\/\/web.poecdn.com\/gen\/image\/WzIzLDEseyJ0IjoibCIsImMiOi04NjI5MTk0fV0\/10d10e4923\/Stash_TabL.png",
            "srcC":"https:\/\/web.poecdn.com\/gen\/image\/WzIzLDEseyJ0IjoibSIsImMiOi04NjI5MTk0fV0\/bc028daabc\/Stash_TabL.png",
            "srcR":"https:\/\/web.poecdn.com\/gen\/image\/WzIzLDEseyJ0IjoiciIsImMiOi04NjI5MTk0fV0\/6aa79009ee\/Stash_TabL.png"
        }
    ],
    "items":[]
}
